stactools/cli/__init__.py
stactools/cli/__main__.py
stactools/cli/cli.py
stactools/cli/py.typed
stactools/cli/registry.py
stactools/cli/commands/__init__.py
stactools/cli/commands/add.py
stactools/cli/commands/add_asset.py
stactools/cli/commands/add_raster.py
stactools/cli/commands/copy.py
stactools/cli/commands/create.py
stactools/cli/commands/info.py
stactools/cli/commands/layout.py
stactools/cli/commands/lint.py
stactools/cli/commands/merge.py
stactools/cli/commands/migrate.py
stactools/cli/commands/summary.py
stactools/cli/commands/update_extent.py
stactools/cli/commands/update_geometry.py
stactools/cli/commands/validate.py
stactools/cli/commands/version.py
stactools/core/__init__.py
stactools/core/add.py
stactools/core/add_asset.py
stactools/core/add_raster.py
stactools/core/copy.py
stactools/core/create.py
stactools/core/geometry.py
stactools/core/layout.py
stactools/core/merge.py
stactools/core/migrate.py
stactools/core/projection.py
stactools/core/py.typed
stactools/core/io/__init__.py
stactools/core/io/xml.py
stactools/core/utils/__init__.py
stactools/core/utils/antimeridian.py
stactools/core/utils/convert.py
stactools/core/utils/raster_footprint.py
stactools/core/utils/round.py
stactools/core/utils/subprocess.py
stactools/testing/__init__.py
stactools/testing/cli.py
stactools/testing/cli_test.py
stactools/testing/py.typed
stactools/testing/test_data.py
stactools-0.5.3.dist-info/LICENSE
stactools-0.5.3.dist-info/METADATA
stactools-0.5.3.dist-info/WHEEL
stactools-0.5.3.dist-info/entry_points.txt
stactools-0.5.3.dist-info/top_level.txt
stactools-0.5.3.dist-info/RECORD
