Metadata-Version: 2.1
Name: stactools
Version: 0.5.3
Summary: Command line tool and Python library for working with STAC
Author-email: Rob Emanuele <rdemanuele@gmail.com>, Pete Gadomski <pete.gadomski@gmail.com>
Maintainer-email: Pete Gadomski <pete.gadomski@gmail.com>
License: Apache-2.0
Project-URL: homepage, https://github.com/stac-utils/stactools
Project-URL: documentation, https://stactools.readthedocs.io/
Project-URL: repository, https://github.com/stac-utils/stactools.git
Project-URL: changelog, https://github.com/stac-utils/stactools/blob/main/CHANGELOG.md
Project-URL: discussions, https://github.com/radiantearth/stac-spec/discussions/categories/stac-software
Keywords: pystac,imagery,raster,catalog,STAC
Classifier: Development Status :: 4 - Beta
Classifier: License :: OSI Approved :: Apache Software License
Classifier: Programming Language :: Python :: 3.8
Classifier: Programming Language :: Python :: 3.9
Classifier: Programming Language :: Python :: 3.10
Classifier: Programming Language :: Python :: 3.11
Requires-Python: >=3.8
License-File: LICENSE
Requires-Dist: antimeridian >=0.2.6
Requires-Dist: click >=8.1.3
Requires-Dist: fsspec[http] >=2021.7
Requires-Dist: lxml >=4.9.2
Requires-Dist: numpy >=1.23.0
Requires-Dist: pyproj >=3.3
Requires-Dist: pystac[validation] >=1.8.2
Requires-Dist: rasterio >=1.3.2
Requires-Dist: shapely >=2.0.1
Provides-Extra: dev
Requires-Dist: black ~=23.3 ; extra == 'dev'
Requires-Dist: codespell ~=2.2 ; extra == 'dev'
Requires-Dist: importlib-metadata ~=6.6 ; extra == 'dev'
Requires-Dist: lxml-stubs ~=0.4 ; extra == 'dev'
Requires-Dist: mypy ~=1.3 ; extra == 'dev'
Requires-Dist: packaging ~=23.1 ; extra == 'dev'
Requires-Dist: pre-commit ~=3.3 ; extra == 'dev'
Requires-Dist: pylint ~=2.17 ; extra == 'dev'
Requires-Dist: pytest-cov ~=3.0 ; extra == 'dev'
Requires-Dist: pytest ~=7.3 ; extra == 'dev'
Requires-Dist: requests >=2.27.1 ; extra == 'dev'
Requires-Dist: ruff ==0.0.265 ; extra == 'dev'
Requires-Dist: types-certifi ~=2021.10.8 ; extra == 'dev'
Requires-Dist: types-orjson ~=3.6 ; extra == 'dev'
Requires-Dist: types-python-dateutil ~=2.8 ; extra == 'dev'
Requires-Dist: types-requests ~=2.30 ; extra == 'dev'
Provides-Extra: docs
Requires-Dist: ipython ~=8.12 ; extra == 'docs'
Requires-Dist: jupyter ~=1.0 ; extra == 'docs'
Requires-Dist: nbsphinx ~=0.9 ; extra == 'docs'
Requires-Dist: pydata-sphinx-theme ~=0.13 ; extra == 'docs'
Requires-Dist: sphinx ~=7.0 ; extra == 'docs'
Requires-Dist: sphinx-autobuild ==2021.3.14 ; extra == 'docs'
Requires-Dist: sphinx-click ~=4.4 ; extra == 'docs'
Requires-Dist: sphinxcontrib-fulltoc ~=1.2 ; extra == 'docs'
Provides-Extra: s3
Requires-Dist: s3fs >=2021.7 ; extra == 's3'
Provides-Extra: validate
Requires-Dist: stac-check >=1.3.2 ; extra == 'validate'
Requires-Dist: stac-validator >=3.1.0 ; extra == 'validate'
